{
  "last_update": "2025-08-10T04:03:28.976310",
  "categories": {
    "reject_domains": {
      "rule_count": 117315,
      "last_updated": "2025-04-12T03:30:20.479414"
    },
    "direct_domains": {
      "rule_count": 129087,
      "last_updated": "2025-04-12T03:30:28.666563"
    },
    "ai_domains": {
      "rule_count": 76,
      "last_updated": "2025-04-12T03:30:32.028288"
    },
    "direct_ips": {
      "rule_count": 208,
      "last_updated": "2025-04-12T03:30:28.697703"
    },
    "netflix": {
      "rule_count": 2258,
      "last_updated": "2025-08-10T04:03:28.652783"
    },
    "disney": {
      "rule_count": 174,
      "last_updated": "2025-08-10T04:03:28.662202"
    },
    "youtube": {
      "rule_count": 2258,
      "last_updated": "2025-08-10T04:03:28.536808"
    },
    "spotify": {
      "rule_count": 30,
      "last_updated": "2025-04-12T03:30:29.448678"
    },
    "tiktok": {
      "rule_count": 28,
      "last_updated": "2025-04-12T03:30:29.565168"
    },
    "microsoft": {
      "rule_count": 675,
      "last_updated": "2025-08-10T04:03:28.783806"
    },
    "github": {
      "rule_count": 31,
      "last_updated": "2025-08-10T04:03:28.785695"
    },
    "telegram": {
      "rule_count": 44,
      "last_updated": "2025-08-10T04:03:28.788115"
    },
    "gaming": {
      "rule_count": 188,
      "last_updated": "2025-08-10T04:03:28.798928"
    },
    "proxy_common": {
      "rule_count": 6561,
      "last_updated": "2025-04-12T03:30:31.422484"
    },
    "apple_domains": {
      "rule_count": 1589,
      "last_updated": "2025-08-10T04:03:28.747511"
    },
    "Cloudflare": {
      "rule_count": 65,
      "last_updated": "2025-04-12T03:30:32.318635"
    },
    "ai_all": {
      "rule_count": 151,
      "last_updated": "2025-08-10T04:03:25.219595"
    },
    "direct_all": {
      "rule_count": 954,
      "last_updated": "2025-08-10T04:03:28.421311"
    },
    "BlockHttpDNS": {
      "rule_count": 0,
      "last_updated": "2025-04-15T10:56:03.725758"
    },
    "Privacy": {
      "rule_count": 0,
      "last_updated": "2025-04-15T10:56:03.725777"
    },
    "AdvertisingTest": {
      "rule_count": 0,
      "last_updated": "2025-04-15T10:56:03.725800"
    },
    "GoogleFCM": {
      "rule_count": 26,
      "last_updated": "2025-08-10T04:03:28.799146"
    },
    "BiliBili": {
      "rule_count": 80,
      "last_updated": "2025-08-10T04:03:28.799555"
    },
    "ad_all": {
      "rule_count": 89744,
      "last_updated": "2025-08-10T04:03:28.365314"
    },
    "privacy_all": {
      "rule_count": 0,
      "last_updated": "2025-04-15T10:56:49.330139"
    },
    "tvb": {
      "rule_count": 7,
      "last_updated": "2025-08-10T04:03:28.662352"
    },
    "ban_pcdn": {
      "rule_count": 33,
      "last_updated": "2025-08-10T04:03:28.931060"
    }
  }
}